wedet/__init__.py
wedet/setting.py
wedet/debug/__init__.py
wedet/debug/persistence.py
wedet/debug/status.py
wedet/imgproc/__init__.py
wedet/imgproc/cutting.py
wedet/plotter/__init__.py
wedet/plotter/line.py
wedet/plotter/log_parser.py
wedet/serial/__init__.py
wedet/serial/dfsim_tx2_client.py
wedet/serial/utils.py
wedet/socket/__init__.py
wedet/socket/mt_client.py
wedet/socket/mt_server.py
wedet/socket/udp_client.py
wedet/socket/utils.py
wedet/structures/__init__.py
wedet/structures/boxes.py
wedet/structures/instances.py
wedet/structures/spire_annotations.py
wedet/structures/class_desc/coco.txt
wedet/structures/class_desc/deepsea_mn.txt
wedet/structures/class_desc/dota.txt
wedet/structures/class_desc/drone_det.txt
wedet/structures/class_desc/fsod_200.txt
wedet/structures/class_desc/fsod_800.txt
wedet/structures/class_desc/visdrone.txt
wedet/structures/class_desc/visdrone_12.txt
wedet/structures/class_desc/visdrone_6.txt
wedet/structures/class_desc/widerface.txt
wedet/structures/class_desc/class_trans/drone_det_5_1.txt
wedet/structures/class_desc/class_trans/visdrone_10_1.txt
wedet/structures/class_desc/class_trans/visdrone_12_10.txt
wedet/structures/class_desc/class_trans/visdrone_80_6.txt
wedet-0.1.2.dist-info/LICENSE
wedet-0.1.2.dist-info/METADATA
wedet-0.1.2.dist-info/WHEEL
wedet-0.1.2.dist-info/top_level.txt
wedet-0.1.2.dist-info/RECORD
