Metadata-Version: 2.1
Name: wedet
Version: 0.1.2
Summary: UNKNOWN
Home-page: UNKNOWN
Author: jario&team
Author-email: jariof@foxmail.com
License: UNKNOWN
Platform: UNKNOWN
Classifier: Programming Language :: Python :: 3
Classifier: Operating System :: OS Independent
Requires-Python: >=3.6
License-File: LICENSE
